orion/algo/skopt/__init__.py
orion/algo/skopt/_version.py
orion/algo/skopt/bayes.py
orion.algo.skopt-0.1.8.dist-info/LICENSE
orion.algo.skopt-0.1.8.dist-info/METADATA
orion.algo.skopt-0.1.8.dist-info/WHEEL
orion.algo.skopt-0.1.8.dist-info/entry_points.txt
orion.algo.skopt-0.1.8.dist-info/top_level.txt
orion.algo.skopt-0.1.8.dist-info/RECORD
