Metadata-Version: 2.1
Name: orion.algo.skopt
Version: 0.1.8
Summary: Implement a wrapper for skopt optimizers.
Home-page: https://github.com/Epistimio/orion.algo.skopt
Author: Epistímio
Author-email: xavier.bouthillier@umontreal.ca
License: BSD-3-Clause
Keywords: Machine Learning,Deep Learning,Distributed,Optimization
Platform: Linux
Classifier: Development Status :: 1 - Planning
Classifier: Intended Audience :: Developers
Classifier: Intended Audience :: Education
Classifier: Intended Audience :: Science/Research
Classifier: License :: OSI Approved :: BSD License
Classifier: Operating System :: POSIX
Classifier: Operating System :: Unix
Classifier: Programming Language :: Python
Classifier: Topic :: Scientific/Engineering
Classifier: Topic :: Scientific/Engineering :: Artificial Intelligence
Classifier: Programming Language :: Python :: 3
Classifier: Programming Language :: Python :: 3.6
Classifier: Programming Language :: Python :: 3.7
Classifier: Programming Language :: Python :: 3.8
Classifier: Programming Language :: Python :: 3.9
License-File: LICENSE
Requires-Dist: orion (>=0.2.2)
Requires-Dist: scikit-optimize (>=0.5.1)
Provides-Extra: test
Requires-Dist: pytest (>=3.0.0) ; extra == 'test'
